mcp_esa_server/__init__.py
mcp_esa_server/esa_client.py
mcp_esa_server/server.py
mcp_esa_server-0.1.8.dist-info/METADATA
mcp_esa_server-0.1.8.dist-info/WHEEL
mcp_esa_server-0.1.8.dist-info/entry_points.txt
mcp_esa_server-0.1.8.dist-info/licenses/LICENSE
mcp_esa_server-0.1.8.dist-info/RECORD
