Metadata-Version: 2.4
Name: mcp-esa-server
Version: 0.1.8
Summary: MCP server for esa.io API
Project-URL: Homepage, https://github.com/scnsh/mcp-esa-server-python
Project-URL: Repository, https://github.com/scnsh/mcp-esa-server-python
Author: scnsh
License-Expression: MIT
License-File: LICENSE
Classifier: Development Status :: 3 - Alpha
Classifier: Intended Audience :: Developers
Classifier: License :: OSI Approved :: MIT License
Classifier: Programming Language :: Python :: 3.11
Classifier: Programming Language :: Python :: 3.12
Classifier: Programming Language :: Python :: 3.13
Requires-Python: >=3.11
Requires-Dist: mcp[cli]>=1.7.1
Requires-Dist: python-dotenv
Requires-Dist: requests
Provides-Extra: dev
Requires-Dist: httpx>=0.28.1; extra == 'dev'
Requires-Dist: pytest-mock>=3.14.0; extra == 'dev'
Requires-Dist: pytest>=8.3.5; extra == 'dev'
Requires-Dist: ruff>=0.11.8; extra == 'dev'
